MANIFEST.in
README.rst
setup.py
RescueDelicious.egg-info/PKG-INFO
RescueDelicious.egg-info/SOURCES.txt
RescueDelicious.egg-info/dependency_links.txt
RescueDelicious.egg-info/entry_points.txt
RescueDelicious.egg-info/not-zip-safe
RescueDelicious.egg-info/requires.txt
RescueDelicious.egg-info/top_level.txt
rescuedel/__init__.py
rescuedel/rescue.py