Metadata-Version: 1.0
Name: RescueDelicious
Version: 0.1.1
Summary: Convert bookmarks in delicious firefox extension to importable file
Home-page: https://github.com/hongqn/rescue-delicious
Author: Qiangning Hong
Author-email: hognqn@gmail.com
License: MIT
Platform: UNKNOWN
Classifier: Development Status :: 4 - Beta
Classifier: Environment :: Console
Classifier: Intended Audience :: End Users/Desktop
Classifier: License :: OSI Approved :: MIT License
Classifier: Programming Language :: Python
Classifier: Topic :: Utilities
